peptides/__init__.py
peptides/datasets/__init__.py
peptides/tables/__init__.py
peptides-0.5.0.dist-info/METADATA
peptides-0.5.0.dist-info/WHEEL
peptides-0.5.0.dist-info/top_level.txt
peptides-0.5.0.dist-info/RECORD
