Metadata-Version: 2.1
Name: peptides
Version: 0.5.0
Summary: Physicochemical properties, indices and descriptors for amino-acid sequences.
Author-email: Martin Larralde <martin.larralde@embl.de>
License:                     GNU GENERAL PUBLIC LICENSE
Project-URL: Bug Tracker, https://github.com/althonos/peptides.py/issues
Project-URL: Changelog, https://github.com/althonos/peptides.py/blob/master/CHANGELOG.md
Project-URL: Coverage, https://codecov.io/gh/althonos/peptides.py/
Project-URL: Builds, https://github.com/althonos/peptides.py/actions
Project-URL: PyPI, https://pypi.org/project/peptides
Keywords: bioinformatics,protein,sequence,peptide,qsar
Classifier: Development Status :: 4 - Beta
Classifier: Intended Audience :: Developers
Classifier: Intended Audience :: Science/Research
Classifier: License :: OSI Approved :: MIT License
Classifier: Operating System :: OS Independent
Classifier: Programming Language :: Python :: 3
Classifier: Topic :: Scientific/Engineering :: Bio-Informatics
Classifier: Topic :: Scientific/Engineering :: Medical Science Apps.
Classifier: Typing :: Typed
Requires-Python: >=3.6
